{"stats":{"minecraft:picked_up":{"minecraft:cookie":19,"minecraft:yellow_wool":19},"minecraft:dropped":{"minecraft:cookie":6},"minecraft:custom":{"minecraft:time_since_rest":2604,"minecraft:leave_game":1,"minecraft:walk_on_water_one_cm":358,"minecraft:damage_dealt":200,"minecraft:crouch_one_cm":5,"minecraft:sprint_one_cm":6946,"minecraft:walk_one_cm":3590,"minecraft:play_time":2604,"minecraft:time_since_death":2604,"minecraft:sneak_time":61,"minecraft:total_world_time":2633,"minecraft:walk_under_water_one_cm":465,"minecraft:mob_kills":1,"minecraft:drop":6,"minecraft:fly_one_cm":26608,"minecraft:jump":11},"minecraft:killed":{"allay:allay":1},"minecraft:used":{"allay:allay_spawn_egg":1,"minecraft:netherite_sword":3}},"DataVersion":2730}